wsi_tissue_tiler/README.md
wsi_tissue_tiler/TissueIdentifier.py
wsi_tissue_tiler/TissueIdentifierModel.py
wsi_tissue_tiler/__init__.py
wsi_tissue_tiler/clip_img_processor/README.md
wsi_tissue_tiler/clip_img_processor/config.json
wsi_tissue_tiler/clip_img_processor/preprocessor_config.json
wsi_tissue_tiler/main.py
wsi_tissue_tiler/requirements.txt
wsi_tissue_tiler/slide_processor.py
wsi_tissue_tiler/tissue_identifier.pth
wsi_tissue_tiler-0.1.0.dist-info/METADATA
wsi_tissue_tiler-0.1.0.dist-info/WHEEL
wsi_tissue_tiler-0.1.0.dist-info/entry_points.txt
wsi_tissue_tiler-0.1.0.dist-info/RECORD
