Metadata-Version: 2.1
Name: wsi-tissue-tiler
Version: 0.1.0
Summary: It makes small patches / tiles of large whole slide images available in svs format.
License: CC-BY-NC-SA-4.0
Author: Vatsal Patel
Author-email: vatsal1804@gmail.com
Requires-Python: >=3.11,<4.0
Classifier: License :: Other/Proprietary License
Classifier: Programming Language :: Python :: 3
Classifier: Programming Language :: Python :: 3.11
Classifier: Programming Language :: Python :: 3.12
Requires-Dist: matplotlib (>=3.9.0,<4.0.0)
Requires-Dist: numpy (>=1.26.4,<2.0.0)
Requires-Dist: openslide-python (>=1.3.1,<2.0.0)
Requires-Dist: pandas (>=2.2.2,<3.0.0)
Requires-Dist: pillow (>=10.3.0,<11.0.0)
Requires-Dist: scikit-image (>=0.23.2,<0.24.0)
Requires-Dist: torch (>=2.3.1,<3.0.0)
Requires-Dist: tqdm (>=4.66.4,<5.0.0)
Requires-Dist: transformers (>=4.41.2,<5.0.0)
